Metadata-Version: 2.1
Name: hippybase
Version: 0.1.2
Summary: A Python library to interact with Apache Hbase through its REST api
Home-page: https://github.com/WeiJiHsiao/hippybase
Author: WeiJi Hsiao
License: MIT License
Platform: UNKNOWN
